click_hotoffthehamster/__init__.py
click_hotoffthehamster/_compat.py
click_hotoffthehamster/_termui_impl.py
click_hotoffthehamster/_textwrap.py
click_hotoffthehamster/_winconsole.py
click_hotoffthehamster/core.py
click_hotoffthehamster/decorators.py
click_hotoffthehamster/exceptions.py
click_hotoffthehamster/formatting.py
click_hotoffthehamster/globals.py
click_hotoffthehamster/parser.py
click_hotoffthehamster/py.typed
click_hotoffthehamster/shell_completion.py
click_hotoffthehamster/termui.py
click_hotoffthehamster/testing.py
click_hotoffthehamster/types.py
click_hotoffthehamster/utils.py
click_hotoffthehamster-7.8.4.dist-info/LICENSE.rst
click_hotoffthehamster-7.8.4.dist-info/METADATA
click_hotoffthehamster-7.8.4.dist-info/WHEEL
click_hotoffthehamster-7.8.4.dist-info/RECORD
