Metadata-Version: 2.1
Name: click-hotoffthehamster
Version: 7.8.4
Summary: Composable command line interface toolkit
License: BSD-3-Clause
Author: Armin Ronacher
Author-email: armin.ronacher@active-4.com
Maintainer: Pallets
Maintainer-email: contact@palletsprojects.com
Requires-Python: >=3.8.1,<4.0.0
Classifier: Development Status :: 5 - Production/Stable
Classifier: Intended Audience :: Developers
Classifier: License :: OSI Approved :: BSD License
Classifier: Operating System :: OS Independent
Classifier: Programming Language :: Python
Classifier: Programming Language :: Python :: 3
Classifier: Programming Language :: Python :: 3.9
Classifier: Programming Language :: Python :: 3.10
Classifier: Programming Language :: Python :: 3.11
Classifier: Programming Language :: Python :: 3.12
Provides-Extra: readthedocs
Requires-Dist: colorama (>=0.4.6,<0.5.0) ; sys_platform == "win32"
Requires-Dist: sphinx (>=6.2.1,<7.0.0) ; (python_version >= "3.8" and python_version < "3.9") and (extra == "readthedocs")
Requires-Dist: sphinx (>=7.2.6,<8.0.0) ; (python_version >= "3.9" and python_version < "4.0") and (extra == "readthedocs")
Requires-Dist: sphinx-rtd-theme (>=2.0.0rc4,<3.0.0) ; extra == "readthedocs"
Requires-Dist: tomli (>=2.0.1) ; extra == "readthedocs"
Project-URL: Changes, https://click.palletsprojects.com/changes/
Project-URL: Chat, https://discord.gg/pallets
Project-URL: Donate, https://palletsprojects.com/donate
Project-URL: Documentation, https://click.palletsprojects.com/
Project-URL: Issue Tracker, https://github.com/pallets/click/issues/
Project-URL: Source Code, https://github.com/pallets/click/
Project-URL: repository, https://github.com/doblabs/click-hotoffthehamster#🪝
